bioregistry/__init__.py
bioregistry/__main__.py
bioregistry/analysis/__init__.py
bioregistry/analysis/bioregistry_diff.py
bioregistry/analysis/mapping_checking.py
bioregistry/analysis/paper_ranking.py
bioregistry/app/__init__.py
bioregistry/app/api.py
bioregistry/app/cli.py
bioregistry/app/constants.py
bioregistry/app/impl.py
bioregistry/app/proxies.py
bioregistry/app/static/czi.svg
bioregistry/app/static/dalia.png
bioregistry/app/static/dfg.svg
bioregistry/app/static/funding-manifest-urls.txt
bioregistry/app/static/logo.svg
bioregistry/app/static/nfdi4chem.svg
bioregistry/app/static/northeastern.svg
bioregistry/app/static/rwth-iac.svg
bioregistry/app/templates/base.html
bioregistry/app/templates/collection.html
bioregistry/app/templates/collections.html
bioregistry/app/templates/context.html
bioregistry/app/templates/contexts.html
bioregistry/app/templates/contributor.html
bioregistry/app/templates/contributors.html
bioregistry/app/templates/highlights/owners.html
bioregistry/app/templates/highlights/relations.html
bioregistry/app/templates/highlights/twitter.html
bioregistry/app/templates/home.html
bioregistry/app/templates/keyword.html
bioregistry/app/templates/keywords.html
bioregistry/app/templates/macros.html
bioregistry/app/templates/meta/access.html
bioregistry/app/templates/meta/acknowledgements.html
bioregistry/app/templates/meta/download.html
bioregistry/app/templates/meta/related.html
bioregistry/app/templates/meta/schema.html
bioregistry/app/templates/meta/summary.html
bioregistry/app/templates/meta/sustainability.html
bioregistry/app/templates/metaresource.html
bioregistry/app/templates/metaresources.html
bioregistry/app/templates/prose.html
bioregistry/app/templates/reference.html
bioregistry/app/templates/resolve_errors/disallowed_identifier.html
bioregistry/app/templates/resolve_errors/invalid_identifier.html
bioregistry/app/templates/resolve_errors/missing_prefix.html
bioregistry/app/templates/resolve_errors/missing_providers.html
bioregistry-0.13.18.dist-info/WHEEL
bioregistry-0.13.18.dist-info/entry_points.txt
bioregistry-0.13.18.dist-info/METADATA
bioregistry-0.13.18.dist-info/RECORD
