Metadata-Version: 2.3
Name: bioregistry
Version: 0.13.18
Summary: Integrated registry of biological databases and nomenclatures
Keywords: snekpack,cookiecutter,databases,biological databases,biomedical databases,persistent identifiers
Author: Charles Tapley Hoyt
Author-email: Charles Tapley Hoyt <cthoyt@gmail.com>
License: MIT License
Classifier: Development Status :: 4 - Beta
Classifier: Environment :: Console
Classifier: Intended Audience :: Developers
Classifier: License :: OSI Approved :: MIT License
Classifier: Operating System :: OS Independent
Classifier: Framework :: Pytest
Classifier: Framework :: tox
Classifier: Framework :: Sphinx
Classifier: Programming Language :: Python
Classifier: Programming Language :: Python :: 3.10
Classifier: Programming Language :: Python :: 3.11
Classifier: Programming Language :: Python :: 3.12
Classifier: Programming Language :: Python :: 3.13
Classifier: Programming Language :: Python :: 3 :: Only
Requires-Dist: requests
Requires-Dist: tqdm
Requires-Dist: pystow>=0.7.7
Requires-Dist: click
Requires-Dist: more-click>=0.1.2
Requires-Dist: pydantic[email]>=2.0
Requires-Dist: curies>=0.12.2
Requires-Dist: pyyaml ; extra == 'align'
Requires-Dist: beautifulsoup4 ; extra == 'align'
Requires-Dist: tabulate ; extra == 'align'
Requires-Dist: defusedxml ; extra == 'align'
Requires-Dist: class-resolver ; extra == 'align'
Requires-Dist: fairsharing-client>=0.1.0 ; extra == 'align'
Requires-Dist: pandas ; extra == 'align'
Requires-Dist: matplotlib ; extra == 'charts'
Requires-Dist: matplotlib-venn ; extra == 'charts'
Requires-Dist: seaborn ; extra == 'charts'
Requires-Dist: pandas ; extra == 'charts'
Requires-Dist: jinja2 ; extra == 'charts'
Requires-Dist: sphinx>=8 ; extra == 'docs'
Requires-Dist: sphinx-rtd-theme>=3.0 ; extra == 'docs'
Requires-Dist: sphinx-click ; extra == 'docs'
Requires-Dist: sphinx-automodapi ; extra == 'docs'
Requires-Dist: autodoc-pydantic ; extra == 'docs'
Requires-Dist: pyyaml ; extra == 'export'
Requires-Dist: rdflib ; extra == 'export'
Requires-Dist: rdflib-jsonld ; extra == 'export'
Requires-Dist: ndex2 ; extra == 'export'
Requires-Dist: more-itertools ; extra == 'gha'
Requires-Dist: click-default-group ; extra == 'health'
Requires-Dist: pandas ; extra == 'health'
Requires-Dist: tabulate ; extra == 'health'
Requires-Dist: pyyaml ; extra == 'health'
Requires-Dist: jinja2 ; extra == 'health'
Requires-Dist: pandas ; extra == 'mapping-checking'
Requires-Dist: sentence-transformers ; extra == 'mapping-checking'
Requires-Dist: pandas ; extra == 'paper-ranking'
Requires-Dist: scikit-learn ; extra == 'paper-ranking'
Requires-Dist: tabulate ; extra == 'paper-ranking'
Requires-Dist: pubmed-downloader>=0.0.12 ; extra == 'paper-ranking'
Requires-Dist: pytest ; extra == 'tests'
Requires-Dist: coverage ; extra == 'tests'
Requires-Dist: more-itertools ; extra == 'tests'
Requires-Dist: httpx ; extra == 'tests'
Requires-Dist: scikit-learn ; extra == 'tests'
Requires-Dist: pyyaml ; extra == 'web'
Requires-Dist: rdflib ; extra == 'web'
Requires-Dist: rdflib-jsonld ; extra == 'web'
Requires-Dist: rdflib-endpoint>=0.5.3 ; extra == 'web'
Requires-Dist: flask>=3.0.0 ; extra == 'web'
Requires-Dist: werkzeug>=3.0.0 ; extra == 'web'
Requires-Dist: fastapi ; extra == 'web'
Requires-Dist: uvicorn ; extra == 'web'
Requires-Dist: bootstrap-flask ; extra == 'web'
Requires-Dist: markdown ; extra == 'web'
Requires-Dist: curies[fastapi] ; extra == 'web'
Requires-Dist: a2wsgi ; extra == 'web'
Requires-Dist: api-analytics[fastapi] ; extra == 'web'
Maintainer: Charles Tapley Hoyt
Maintainer-email: Charles Tapley Hoyt <cthoyt@gmail.com>
Requires-Python: >=3.10
Project-URL: Bug Tracker, https://github.com/biopragmatics/bioregistry/issues
Project-URL: Homepage, https://github.com/biopragmatics/bioregistry
Project-URL: Repository, https://github.com/biopragmatics/bioregistry.git
Project-URL: Documentation, https://bioregistry.readthedocs.io
Provides-Extra: align
Provides-Extra: charts
Provides-Extra: docs
Provides-Extra: export
Provides-Extra: gha
Provides-Extra: health
Provides-Extra: mapping-checking
Provides-Extra: paper-ranking
Provides-Extra: tests
Provides-Extra: web
